MANIFEST.in
README.md
setup.py
drf_base64/__init__.py
drf_base64/fields.py
drf_base64/serializers.py
drf_base64.egg-info/PKG-INFO
drf_base64.egg-info/SOURCES.txt
drf_base64.egg-info/dependency_links.txt
drf_base64.egg-info/requires.txt
drf_base64.egg-info/top_level.txt